{"_path":"/","_dir":"","_draft":false,"_partial":false,"_locale":"en","_empty":false,"title":"开始","description":"","navigation":false,"layout":"page","body":{"type":"root","children":[{"type":"element","tag":"block-hero","props":{"snippet":"npm i @holyhigh/func.js","type":"success"},"children":[{"type":"element","tag":"template","props":{"v-slot:title":""},"children":[{"type":"element","tag":"p","props":{},"children":[{"type":"text","value":"纯函数, 更专注"}]}]},{"type":"element","tag":"template","props":{"v-slot:description":""},"children":[{"type":"element","tag":"p","props":{},"children":[{"type":"element","tag":"strong","props":{},"children":[{"type":"text","value":"Func.js"}]},{"type":"text","value":"是一个纯函数工具库，通过一致化接口、多种类覆盖等特性为您提供便捷、全面的声明式开发体验。"}]}]},{"type":"element","tag":"template","props":{"v-slot:extra":""},"children":[{"type":"element","tag":"list","props":{"icon":"ph:check","type":"success"},"children":[{"type":"element","tag":"ul","props":{},"children":[{"type":"element","tag":"li","props":{},"children":[{"type":"text","value":"使用TypeScript实现"}]},{"type":"element","tag":"li","props":{},"children":[{"type":"text","value":"各种环境(node.js/browser/electron/nw.js/...)都能用"}]},{"type":"element","tag":"li","props":{},"children":[{"type":"text","value":"各种浏览器(除了IE)都支持"}]},{"type":"element","tag":"li","props":{},"children":[{"type":"text","value":"列表推导、函数管道、谓词签名、泛型..."}]}]}]}]},{"type":"element","tag":"template","props":{"v-slot:actions":""},"children":[{"type":"element","tag":"button-class","props":{"href":"/doc/getting-started","icon":"octicon:feed-rocket-16"},"children":[{"type":"text","value":"马上开始"}]},{"type":"element","tag":"p","props":{},"children":[{"type":"element","tag":"a","props":{":target":"_blank","href":"https://stackblitz.com/edit/func-js?file=index.ts","rel":["nofollow"]},"children":[{"type":"text","value":"⚡ Play on StackBlitz"}]}]}]}]},{"type":"element","tag":"card-grid","props":{},"children":[{"type":"element","tag":"template","props":{"v-slot:title":""},"children":[{"type":"element","tag":"p","props":{},"children":[{"type":"text","value":"强大特性"}]}]},{"type":"element","tag":"template","props":{"v-slot:root":""},"children":[{"type":"element","tag":"ellipsis","props":{"blur":"140px","left":"0px","top":"10rem","width":"40rem"},"children":[]}]},{"type":"element","tag":"card","props":{"icon":"mdi:all-inclusive-box-outline"},"children":[{"type":"element","tag":"template","props":{"v-slot:title":""},"children":[{"type":"element","tag":"p","props":{},"children":[{"type":"text","value":"一致化"}]}]},{"type":"element","tag":"template","props":{"v-slot:description":""},"children":[{"type":"element","tag":"p","props":{},"children":[{"type":"text","value":"接口，一个Api适用所有集合类型。所有集合类函数都使用一致化封装方式。"}]},{"type":"element","tag":"code","props":{"code":"//遍历对象\neach({'1':'a','2':'b'},...)\n//遍历DOM\neach(document.body.children,...)\n//遍历数组\neach([1,2,3],...)\n//遍历Set\neach(new Set([1,2,3],...)\n","language":"js","meta":null},"children":[{"type":"element","tag":"pre","props":{},"children":[{"type":"element","tag":"code","props":{"__ignoreMap":""},"children":[{"type":"element","tag":"span","props":{"class":"line"},"children":[{"type":"element","tag":"span","props":{"class":"ct-50e544"},"children":[{"type":"text","value":"//遍历对象"}]}]},{"type":"element","tag":"span","props":{"class":"line"},"children":[{"type":"element","tag":"span","props":{"class":"ct-2d69a0"},"children":[{"type":"text","value":"each"}]},{"type":"element","tag":"span","props":{"class":"ct-253774"},"children":[{"type":"text","value":"({"}]},{"type":"element","tag":"span","props":{"class":"ct-270f54"},"children":[{"type":"text","value":"'1'"}]},{"type":"element","tag":"span","props":{"class":"ct-253774"},"children":[{"type":"text","value":":"}]},{"type":"element","tag":"span","props":{"class":"ct-270f54"},"children":[{"type":"text","value":"'a'"}]},{"type":"element","tag":"span","props":{"class":"ct-253774"},"children":[{"type":"text","value":","}]},{"type":"element","tag":"span","props":{"class":"ct-270f54"},"children":[{"type":"text","value":"'2'"}]},{"type":"element","tag":"span","props":{"class":"ct-253774"},"children":[{"type":"text","value":":"}]},{"type":"element","tag":"span","props":{"class":"ct-270f54"},"children":[{"type":"text","value":"'b'"}]},{"type":"element","tag":"span","props":{"class":"ct-253774"},"children":[{"type":"text","value":"},"}]},{"type":"element","tag":"span","props":{"class":"ct-cf281f"},"children":[{"type":"text","value":"..."}]},{"type":"element","tag":"span","props":{"class":"ct-253774"},"children":[{"type":"text","value":")"}]}]},{"type":"element","tag":"span","props":{"class":"line"},"children":[{"type":"element","tag":"span","props":{"class":"ct-50e544"},"children":[{"type":"text","value":"//遍历DOM"}]}]},{"type":"element","tag":"span","props":{"class":"line"},"children":[{"type":"element","tag":"span","props":{"class":"ct-2d69a0"},"children":[{"type":"text","value":"each"}]},{"type":"element","tag":"span","props":{"class":"ct-253774"},"children":[{"type":"text","value":"(document.body.children,"}]},{"type":"element","tag":"span","props":{"class":"ct-cf281f"},"children":[{"type":"text","value":"..."}]},{"type":"element","tag":"span","props":{"class":"ct-253774"},"children":[{"type":"text","value":")"}]}]},{"type":"element","tag":"span","props":{"class":"line"},"children":[{"type":"element","tag":"span","props":{"class":"ct-50e544"},"children":[{"type":"text","value":"//遍历数组"}]}]},{"type":"element","tag":"span","props":{"class":"line"},"children":[{"type":"element","tag":"span","props":{"class":"ct-2d69a0"},"children":[{"type":"text","value":"each"}]},{"type":"element","tag":"span","props":{"class":"ct-253774"},"children":[{"type":"text","value":"(["}]},{"type":"element","tag":"span","props":{"class":"ct-4274ff"},"children":[{"type":"text","value":"1"}]},{"type":"element","tag":"span","props":{"class":"ct-253774"},"children":[{"type":"text","value":","}]},{"type":"element","tag":"span","props":{"class":"ct-4274ff"},"children":[{"type":"text","value":"2"}]},{"type":"element","tag":"span","props":{"class":"ct-253774"},"children":[{"type":"text","value":","}]},{"type":"element","tag":"span","props":{"class":"ct-4274ff"},"children":[{"type":"text","value":"3"}]},{"type":"element","tag":"span","props":{"class":"ct-253774"},"children":[{"type":"text","value":"],"}]},{"type":"element","tag":"span","props":{"class":"ct-cf281f"},"children":[{"type":"text","value":"..."}]},{"type":"element","tag":"span","props":{"class":"ct-253774"},"children":[{"type":"text","value":")"}]}]},{"type":"element","tag":"span","props":{"class":"line"},"children":[{"type":"element","tag":"span","props":{"class":"ct-50e544"},"children":[{"type":"text","value":"//遍历Set"}]}]},{"type":"element","tag":"span","props":{"class":"line"},"children":[{"type":"element","tag":"span","props":{"class":"ct-2d69a0"},"children":[{"type":"text","value":"each"}]},{"type":"element","tag":"span","props":{"class":"ct-253774"},"children":[{"type":"text","value":"("}]},{"type":"element","tag":"span","props":{"class":"ct-cf281f"},"children":[{"type":"text","value":"new"}]},{"type":"element","tag":"span","props":{"class":"ct-253774"},"children":[{"type":"text","value":" "}]},{"type":"element","tag":"span","props":{"class":"ct-2d69a0"},"children":[{"type":"text","value":"Set"}]},{"type":"element","tag":"span","props":{"class":"ct-253774"},"children":[{"type":"text","value":"(["}]},{"type":"element","tag":"span","props":{"class":"ct-4274ff"},"children":[{"type":"text","value":"1"}]},{"type":"element","tag":"span","props":{"class":"ct-253774"},"children":[{"type":"text","value":","}]},{"type":"element","tag":"span","props":{"class":"ct-4274ff"},"children":[{"type":"text","value":"2"}]},{"type":"element","tag":"span","props":{"class":"ct-253774"},"children":[{"type":"text","value":","}]},{"type":"element","tag":"span","props":{"class":"ct-4274ff"},"children":[{"type":"text","value":"3"}]},{"type":"element","tag":"span","props":{"class":"ct-253774"},"children":[{"type":"text","value":"],"}]},{"type":"element","tag":"span","props":{"class":"ct-cf281f"},"children":[{"type":"text","value":"..."}]},{"type":"element","tag":"span","props":{"class":"ct-253774"},"children":[{"type":"text","value":")"}]}]}]}]}]}]}]},{"type":"element","tag":"card","props":{"icon":"material-symbols:diversity-2-outline"},"children":[{"type":"element","tag":"template","props":{"v-slot:title":""},"children":[{"type":"element","tag":"p","props":{},"children":[{"type":"text","value":"多种类"}]}]},{"type":"element","tag":"template","props":{"v-slot:description":""},"children":[{"type":"element","tag":"p","props":{},"children":[{"type":"text","value":"函数，包含13个模块共200+个纯函数可助您专注于业务。"}]},{"type":"element","tag":"code","props":{"code":"//将array结构数据变为tree结构数据\narrayToTree(data,'id','pid')\n//生成一个指定长度的alphaId并返回\nalphaId(28)\n//忽略大小写包含判断\ntest('func.js','Func','i')\n//格式化为科学计数法\nformatNumber(-0.01234,'##.0000E')\n","language":"ts","meta":null},"children":[{"type":"element","tag":"pre","props":{},"children":[{"type":"element","tag":"code","props":{"__ignoreMap":""},"children":[{"type":"element","tag":"span","props":{"class":"line"},"children":[{"type":"element","tag":"span","props":{"class":"ct-50e544"},"children":[{"type":"text","value":"//将array结构数据变为tree结构数据"}]}]},{"type":"element","tag":"span","props":{"class":"line"},"children":[{"type":"element","tag":"span","props":{"class":"ct-2d69a0"},"children":[{"type":"text","value":"arrayToTree"}]},{"type":"element","tag":"span","props":{"class":"ct-253774"},"children":[{"type":"text","value":"(data,"}]},{"type":"element","tag":"span","props":{"class":"ct-270f54"},"children":[{"type":"text","value":"'id'"}]},{"type":"element","tag":"span","props":{"class":"ct-253774"},"children":[{"type":"text","value":","}]},{"type":"element","tag":"span","props":{"class":"ct-270f54"},"children":[{"type":"text","value":"'pid'"}]},{"type":"element","tag":"span","props":{"class":"ct-253774"},"children":[{"type":"text","value":")"}]}]},{"type":"element","tag":"span","props":{"class":"line"},"children":[{"type":"element","tag":"span","props":{"class":"ct-50e544"},"children":[{"type":"text","value":"//生成一个指定长度的alphaId并返回"}]}]},{"type":"element","tag":"span","props":{"class":"line"},"children":[{"type":"element","tag":"span","props":{"class":"ct-2d69a0"},"children":[{"type":"text","value":"alphaId"}]},{"type":"element","tag":"span","props":{"class":"ct-253774"},"children":[{"type":"text","value":"("}]},{"type":"element","tag":"span","props":{"class":"ct-4274ff"},"children":[{"type":"text","value":"28"}]},{"type":"element","tag":"span","props":{"class":"ct-253774"},"children":[{"type":"text","value":")"}]}]},{"type":"element","tag":"span","props":{"class":"line"},"children":[{"type":"element","tag":"span","props":{"class":"ct-50e544"},"children":[{"type":"text","value":"//忽略大小写包含判断"}]}]},{"type":"element","tag":"span","props":{"class":"line"},"children":[{"type":"element","tag":"span","props":{"class":"ct-2d69a0"},"children":[{"type":"text","value":"test"}]},{"type":"element","tag":"span","props":{"class":"ct-253774"},"children":[{"type":"text","value":"("}]},{"type":"element","tag":"span","props":{"class":"ct-270f54"},"children":[{"type":"text","value":"'func.js'"}]},{"type":"element","tag":"span","props":{"class":"ct-253774"},"children":[{"type":"text","value":","}]},{"type":"element","tag":"span","props":{"class":"ct-270f54"},"children":[{"type":"text","value":"'Func'"}]},{"type":"element","tag":"span","props":{"class":"ct-253774"},"children":[{"type":"text","value":","}]},{"type":"element","tag":"span","props":{"class":"ct-270f54"},"children":[{"type":"text","value":"'i'"}]},{"type":"element","tag":"span","props":{"class":"ct-253774"},"children":[{"type":"text","value":")"}]}]},{"type":"element","tag":"span","props":{"class":"line"},"children":[{"type":"element","tag":"span","props":{"class":"ct-50e544"},"children":[{"type":"text","value":"//格式化为科学计数法"}]}]},{"type":"element","tag":"span","props":{"class":"line"},"children":[{"type":"element","tag":"span","props":{"class":"ct-2d69a0"},"children":[{"type":"text","value":"formatNumber"}]},{"type":"element","tag":"span","props":{"class":"ct-253774"},"children":[{"type":"text","value":"("}]},{"type":"element","tag":"span","props":{"class":"ct-cf281f"},"children":[{"type":"text","value":"-"}]},{"type":"element","tag":"span","props":{"class":"ct-4274ff"},"children":[{"type":"text","value":"0.01234"}]},{"type":"element","tag":"span","props":{"class":"ct-253774"},"children":[{"type":"text","value":","}]},{"type":"element","tag":"span","props":{"class":"ct-270f54"},"children":[{"type":"text","value":"'##.0000E'"}]},{"type":"element","tag":"span","props":{"class":"ct-253774"},"children":[{"type":"text","value":")"}]}]}]}]}]}]}]},{"type":"element","tag":"card","props":{"icon":"typcn:flash-outline"},"children":[{"type":"element","tag":"template","props":{"v-slot:title":""},"children":[{"type":"element","tag":"p","props":{},"children":[{"type":"text","value":"高性能"}]}]},{"type":"element","tag":"template","props":{"v-slot:description":""},"children":[{"type":"element","tag":"p","props":{},"children":[{"type":"text","value":"算法，通过列表推导可对集合操作进行优化并大幅提升性能。"}]},{"type":"element","tag":"code","props":{"code":"//[19999998, 19999996, 19999994]\n//仅循环 18 次\n_(_.range(20000000))\n.map((v) => v+1)\n.filter((v) => v%2==0)\n.reverse()\n.slice(1, 4)\n.value()\n","language":"ts","meta":null},"children":[{"type":"element","tag":"pre","props":{},"children":[{"type":"element","tag":"code","props":{"__ignoreMap":""},"children":[{"type":"element","tag":"span","props":{"class":"line"},"children":[{"type":"element","tag":"span","props":{"class":"ct-50e544"},"children":[{"type":"text","value":"//[19999998, 19999996, 19999994]"}]}]},{"type":"element","tag":"span","props":{"class":"line"},"children":[{"type":"element","tag":"span","props":{"class":"ct-50e544"},"children":[{"type":"text","value":"//仅循环 18 次"}]}]},{"type":"element","tag":"span","props":{"class":"line"},"children":[{"type":"element","tag":"span","props":{"class":"ct-2d69a0"},"children":[{"type":"text","value":"_"}]},{"type":"element","tag":"span","props":{"class":"ct-253774"},"children":[{"type":"text","value":"(_."}]},{"type":"element","tag":"span","props":{"class":"ct-2d69a0"},"children":[{"type":"text","value":"range"}]},{"type":"element","tag":"span","props":{"class":"ct-253774"},"children":[{"type":"text","value":"("}]},{"type":"element","tag":"span","props":{"class":"ct-4274ff"},"children":[{"type":"text","value":"20000000"}]},{"type":"element","tag":"span","props":{"class":"ct-253774"},"children":[{"type":"text","value":"))"}]}]},{"type":"element","tag":"span","props":{"class":"line"},"children":[{"type":"element","tag":"span","props":{"class":"ct-253774"},"children":[{"type":"text","value":"."}]},{"type":"element","tag":"span","props":{"class":"ct-2d69a0"},"children":[{"type":"text","value":"map"}]},{"type":"element","tag":"span","props":{"class":"ct-253774"},"children":[{"type":"text","value":"(("}]},{"type":"element","tag":"span","props":{"class":"ct-21265b"},"children":[{"type":"text","value":"v"}]},{"type":"element","tag":"span","props":{"class":"ct-253774"},"children":[{"type":"text","value":") "}]},{"type":"element","tag":"span","props":{"class":"ct-cf281f"},"children":[{"type":"text","value":"=>"}]},{"type":"element","tag":"span","props":{"class":"ct-253774"},"children":[{"type":"text","value":" v"}]},{"type":"element","tag":"span","props":{"class":"ct-cf281f"},"children":[{"type":"text","value":"+"}]},{"type":"element","tag":"span","props":{"class":"ct-4274ff"},"children":[{"type":"text","value":"1"}]},{"type":"element","tag":"span","props":{"class":"ct-253774"},"children":[{"type":"text","value":")"}]}]},{"type":"element","tag":"span","props":{"class":"line"},"children":[{"type":"element","tag":"span","props":{"class":"ct-253774"},"children":[{"type":"text","value":"."}]},{"type":"element","tag":"span","props":{"class":"ct-2d69a0"},"children":[{"type":"text","value":"filter"}]},{"type":"element","tag":"span","props":{"class":"ct-253774"},"children":[{"type":"text","value":"(("}]},{"type":"element","tag":"span","props":{"class":"ct-21265b"},"children":[{"type":"text","value":"v"}]},{"type":"element","tag":"span","props":{"class":"ct-253774"},"children":[{"type":"text","value":") "}]},{"type":"element","tag":"span","props":{"class":"ct-cf281f"},"children":[{"type":"text","value":"=>"}]},{"type":"element","tag":"span","props":{"class":"ct-253774"},"children":[{"type":"text","value":" v"}]},{"type":"element","tag":"span","props":{"class":"ct-cf281f"},"children":[{"type":"text","value":"%"}]},{"type":"element","tag":"span","props":{"class":"ct-4274ff"},"children":[{"type":"text","value":"2"}]},{"type":"element","tag":"span","props":{"class":"ct-cf281f"},"children":[{"type":"text","value":"=="}]},{"type":"element","tag":"span","props":{"class":"ct-4274ff"},"children":[{"type":"text","value":"0"}]},{"type":"element","tag":"span","props":{"class":"ct-253774"},"children":[{"type":"text","value":")"}]}]},{"type":"element","tag":"span","props":{"class":"line"},"children":[{"type":"element","tag":"span","props":{"class":"ct-253774"},"children":[{"type":"text","value":"."}]},{"type":"element","tag":"span","props":{"class":"ct-2d69a0"},"children":[{"type":"text","value":"reverse"}]},{"type":"element","tag":"span","props":{"class":"ct-253774"},"children":[{"type":"text","value":"()"}]}]},{"type":"element","tag":"span","props":{"class":"line"},"children":[{"type":"element","tag":"span","props":{"class":"ct-253774"},"children":[{"type":"text","value":"."}]},{"type":"element","tag":"span","props":{"class":"ct-2d69a0"},"children":[{"type":"text","value":"slice"}]},{"type":"element","tag":"span","props":{"class":"ct-253774"},"children":[{"type":"text","value":"("}]},{"type":"element","tag":"span","props":{"class":"ct-4274ff"},"children":[{"type":"text","value":"1"}]},{"type":"element","tag":"span","props":{"class":"ct-253774"},"children":[{"type":"text","value":", "}]},{"type":"element","tag":"span","props":{"class":"ct-4274ff"},"children":[{"type":"text","value":"4"}]},{"type":"element","tag":"span","props":{"class":"ct-253774"},"children":[{"type":"text","value":")"}]}]},{"type":"element","tag":"span","props":{"class":"line"},"children":[{"type":"element","tag":"span","props":{"class":"ct-253774"},"children":[{"type":"text","value":"."}]},{"type":"element","tag":"span","props":{"class":"ct-2d69a0"},"children":[{"type":"text","value":"value"}]},{"type":"element","tag":"span","props":{"class":"ct-253774"},"children":[{"type":"text","value":"()"}]}]}]}]}]}]}]}]},{"type":"element","tag":"card","props":{"icon":"logos:typescript-icon",":blurry":"false"},"children":[{"type":"element","tag":"template","props":{"v-slot:title":""},"children":[{"type":"element","tag":"p","props":{},"children":[{"type":"text","value":"TypeScript支持"}]}]},{"type":"element","tag":"template","props":{"v-slot:description":""},"children":[{"type":"element","tag":"p","props":{},"children":[{"type":"text","value":"Func.js使用TS构建，所有函数都具有明确返回类型。\n在集合与数组模块中，大部分函数都具有基于泛型或参数的多签名重载"}]},{"type":"element","tag":"blockquote","props":{},"children":[{"type":"element","tag":"p","props":{},"children":[{"type":"element","tag":"icon","props":{"name":"fe:info"},"children":[]},{"type":"text","value":"鼠标悬浮在参数上可查看类型；按住Ctrl并点击函数可查看签名"}]}]},{"type":"element","tag":"monaco-editor-home","props":{},"children":[]}]}]},{"type":"element","tag":"style","children":[{"type":"text","value":".ct-21265b{color:#953800}\n.ct-4274ff{color:#0550AE}\n.ct-cf281f{color:#CF222E}\n.ct-270f54{color:#0A3069}\n.ct-253774{color:#24292F}\n.ct-2d69a0{color:#8250DF}\n.ct-50e544{color:#6E7781}\n.dark .ct-50e544{color:#8B949E}\n.dark .ct-2d69a0{color:#D2A8FF}\n.dark .ct-253774{color:#C9D1D9}\n.dark .ct-270f54{color:#A5D6FF}\n.dark .ct-cf281f{color:#FF7B72}\n.dark .ct-4274ff{color:#79C0FF}\n.dark .ct-21265b{color:#FFA657}"}]}],"toc":{"title":"","searchDepth":2,"depth":2,"links":[]}},"_type":"markdown","_id":"content:0.index.md","_source":"content","_file":"0.index.md","_extension":"md"}